detect_shadowed_modules/__init__.py
detect_shadowed_modules/editable.py
detect_shadowed_modules-0.2.0.dist-info/WHEEL
detect_shadowed_modules-0.2.0.dist-info/entry_points.txt
detect_shadowed_modules-0.2.0.dist-info/METADATA
detect_shadowed_modules-0.2.0.dist-info/RECORD
