Metadata-Version: 2.3
Name: detect-shadowed-modules
Version: 0.2.0
Summary: Detect conflicting directory names across Python's sys.path that shadow installed packages
Keywords: import,shadowing,diagnostics
Author: Michael Bianco
Author-email: Michael Bianco <mike@mikebian.co>
Requires-Python: >=3.11
Project-URL: Repository, https://github.com/iloveitaly/detect-shadowed-modules
